{"indexes":[],"parameters":{"allowUserKeys":true,"cacheEnabled":false,"cid":"2581","deleted":false,"globallyUniqueId":"h2839D6DD30D5/29523005","id":"2581","isDisjoint":false,"isSmart":false,"isSmartChild":false,"isSystem":false,"keyOptions":{"allowUserKeys":true,"type":"traditional","lastValue":30419109},"minReplicationFactor":1,"name":"citing","numberOfShards":1,"planId":"29523005","replicationFactor":1,"schema":null,"shardKeys":["_key"],"shards":{},"status":3,"tempObjectId":"0","type":3,"version":9,"waitForSync":false,"writeConcern":1}}